TensorflowTuxiangShenduXuexiShiyongZhinanChuyiFix1/README.md
TensorflowTuxiangShenduXuexiShiyongZhinanChuyiFix1/__init__.py
TensorflowTuxiangShenduXuexiShiyongZhinanChuyiFix1/__main__.py
TensorflowTuxiangShenduXuexiShiyongZhinanChuyiFix1/file.epub
TensorflowTuxiangShenduXuexiShiyongZhinanChuyiFix1/index.html
TensorflowTuxiangShenduXuexiShiyongZhinanChuyiFix1/css/__init__.py
TensorflowTuxiangShenduXuexiShiyongZhinanChuyiFix1/css/annotations.css
TensorflowTuxiangShenduXuexiShiyongZhinanChuyiFix1/css/main.css
TensorflowTuxiangShenduXuexiShiyongZhinanChuyiFix1/css/normalize.css
TensorflowTuxiangShenduXuexiShiyongZhinanChuyiFix1/css/popup.css
TensorflowTuxiangShenduXuexiShiyongZhinanChuyiFix1/font/__init__.py
TensorflowTuxiangShenduXuexiShiyongZhinanChuyiFix1/font/fontello.eot
TensorflowTuxiangShenduXuexiShiyongZhinanChuyiFix1/font/fontello.svg
TensorflowTuxiangShenduXuexiShiyongZhinanChuyiFix1/font/fontello.ttf
TensorflowTuxiangShenduXuexiShiyongZhinanChuyiFix1/font/fontello.woff
TensorflowTuxiangShenduXuexiShiyongZhinanChuyiFix1/img/__init__.py
TensorflowTuxiangShenduXuexiShiyongZhinanChuyiFix1/img/annotator-glyph-sprite.png
TensorflowTuxiangShenduXuexiShiyongZhinanChuyiFix1/img/annotator-icon-sprite.png
TensorflowTuxiangShenduXuexiShiyongZhinanChuyiFix1/img/apple-touch-icon.png
TensorflowTuxiangShenduXuexiShiyongZhinanChuyiFix1/img/cancelfullscreen.png
TensorflowTuxiangShenduXuexiShiyongZhinanChuyiFix1/img/close.png
TensorflowTuxiangShenduXuexiShiyongZhinanChuyiFix1/img/fullscreen.png
TensorflowTuxiangShenduXuexiShiyongZhinanChuyiFix1/img/loader.gif
TensorflowTuxiangShenduXuexiShiyongZhinanChuyiFix1/img/menu-icon.png
TensorflowTuxiangShenduXuexiShiyongZhinanChuyiFix1/img/save.png
TensorflowTuxiangShenduXuexiShiyongZhinanChuyiFix1/img/saved.png
TensorflowTuxiangShenduXuexiShiyongZhinanChuyiFix1/img/settings-s.png
TensorflowTuxiangShenduXuexiShiyongZhinanChuyiFix1/img/settings.png
TensorflowTuxiangShenduXuexiShiyongZhinanChuyiFix1/img/star.png
tensorflow_tuxiang_shendu_xuexi_shiyong_zhinan_chuyi_fix1-2025.3.25.0.dist-info/METADATA
tensorflow_tuxiang_shendu_xuexi_shiyong_zhinan_chuyi_fix1-2025.3.25.0.dist-info/WHEEL
tensorflow_tuxiang_shendu_xuexi_shiyong_zhinan_chuyi_fix1-2025.3.25.0.dist-info/entry_points.txt
tensorflow_tuxiang_shendu_xuexi_shiyong_zhinan_chuyi_fix1-2025.3.25.0.dist-info/top_level.txt
tensorflow_tuxiang_shendu_xuexi_shiyong_zhinan_chuyi_fix1-2025.3.25.0.dist-info/RECORD
